ngen_apigw/__init__.py
ngen_apigw/cli.py
ngen_apigw-0.1.4.dist-info/METADATA
ngen_apigw-0.1.4.dist-info/WHEEL
ngen_apigw-0.1.4.dist-info/entry_points.txt
ngen_apigw-0.1.4.dist-info/top_level.txt
ngen_apigw-0.1.4.dist-info/RECORD
