Metadata-Version: 2.4
Name: ngen-apigw
Version: 0.1.4
Summary: GitOps-friendly API Gateway Configuration Tool
Author: ngen-apigw contributors
License: MIT
Keywords: cli,apigateway,gitops,api
Classifier: Development Status :: 3 - Alpha
Classifier: Intended Audience :: Developers
Classifier: Programming Language :: Python :: 3
Requires-Python: >=3.7
